ccxt_unmerged/__init__.py
ccxt_unmerged/_ccxtUnmergedExchange.py
ccxt_unmerged/bitkub.py
ccxt_unmerged/btse.py
ccxt_unmerged/changellypro.py
ccxt_unmerged/coindcx.py
ccxt_unmerged/foblgate.py
ccxt_unmerged/gateiofutures.py
ccxt_unmerged/nominex.py
ccxt_unmerged/remitano.py
ccxt_unmerged/async_support/__init__.py
ccxt_unmerged/async_support/bitkub.py
ccxt_unmerged/async_support/btse.py
ccxt_unmerged/async_support/changellypro.py
ccxt_unmerged/async_support/coindcx.py
ccxt_unmerged/async_support/foblgate.py
ccxt_unmerged/async_support/gateiofutures.py
ccxt_unmerged/async_support/nominex.py
ccxt_unmerged/async_support/remitano.py
ccxt_unmerged-4.0.dist-info/METADATA
ccxt_unmerged-4.0.dist-info/WHEEL
ccxt_unmerged-4.0.dist-info/top_level.txt
ccxt_unmerged-4.0.dist-info/RECORD
