Metadata-Version: 2.1
Name: ccxt-unmerged
Version: 4.0
Summary: Some 40 exchanges that haven't been merged into ccxt yet.
Home-page: https://github.com/binares/ccxt-unmerged
Author: binares
Author-email: binares@protonmail.com
Requires-Dist: ccxt
